outpost/__init__.py
outpost/files.py
outpost/filterinc.py
outpost/filtermanager.py
outpost/proxy.py
outpost/server.py
outpost/scaffolds/__init__.py
outpost/scaffolds/default/run
outpost/scaffolds/default/server.ini_tmpl
outpost/scaffolds/default/files/index.html
outpost/tests/__init__.py
outpost/tests/client.py
outpost/tests/links.json
outpost/tests/test_filterinc.py
outpost/tests/test_filtermanager.py
outpost/tests/tmpl.pt
outpost-0.5.2.dist-info/METADATA
outpost-0.5.2.dist-info/WHEEL
outpost-0.5.2.dist-info/entry_points.txt
outpost-0.5.2.dist-info/top_level.txt
outpost-0.5.2.dist-info/RECORD
